taf/__init__.py
taf/auth_repo.py
taf/config.py
taf/constants.py
taf/exceptions.py
taf/git.py
taf/keys.py
taf/keystore.py
taf/log.py
taf/messages.py
taf/pygit.py
taf/repositoriesdb.py
taf/repository_utils.py
taf/settings.py
taf/utils.py
taf/validation.py
taf/api/__init__.py
taf/api/api_workflow.py
taf/api/conf.py
taf/api/dependencies.py
taf/api/keystore.py
taf/api/metadata.py
taf/api/repository.py
taf/api/roles.py
taf/api/targets.py
taf/api/yubikey.py
taf/api/utils/__init__.py
taf/api/utils/_conf.py
taf/api/utils/_git.py
taf/libs/__init__.py
taf/models/converter.py
taf/models/models.py
taf/models/types.py
taf/models/validators.py
taf/resources/pre-push
taf/tests/__init__.py
taf/tests/conftest.py
taf/tests/test_utils.py
taf/tests/utils.py
taf/tests/test_api/__init__.py
taf/tests/test_api/conftest.py
taf/tests/test_api/test_repositories_data_model.py
taf/tests/test_api/util.py
taf/tests/test_api/conf/__init__.py
taf/tests/test_api/conf/api/__init__.py
taf/tests/test_api/conf/cli/__init__.py
taf/tests/test_api/conf/cli/test_conf_init_cmd.py
taf/tests/test_api/dependencies/__init__.py
taf/tests/test_api/dependencies/api/__init__.py
taf/tests/test_api/dependencies/api/test_dependencies.py
taf/tests/test_api/dependencies/cli/__init__.py
taf/tests/test_api/dependencies/cli/test_dependencies_cmds.py
taf/tests/test_api/metadata/__init__.py
taf/tests/test_api/metadata/api/__init__.py
taf/tests/test_api/metadata/api/test_metadata.py
taf/tests/test_api/metadata/cli/__init__.py
taf/tests/test_api/repo/__init__.py
taf/tests/test_api/repo/api/__init__.py
taf/tests/test_api/repo/api/test_create_repository.py
taf/tests/test_api/repo/cli/__init__.py
taf/tests/test_api/repo/cli/test_repo_create_cmd.py
taf/tests/test_api/roles/__init__.py
taf/tests/test_api/roles/api/__init__.py
taf/tests/test_api/roles/api/test_roles.py
taf/tests/test_api/roles/cli/__init__.py
taf/tests/test_api/roles/cli/test_roles_cmds.py
taf/tests/test_api/targets/__init__.py
taf-0.37.1.dist-info/licenses/LICENSE.md
taf-0.37.1.dist-info/METADATA
taf-0.37.1.dist-info/WHEEL
taf-0.37.1.dist-info/entry_points.txt
taf-0.37.1.dist-info/top_level.txt
taf-0.37.1.dist-info/RECORD
