Metadata-Version: 2.4
Name: taf
Version: 0.37.1
Summary: Implementation of archival authentication
Home-page: https://github.com/openlawlibrary/taf/tree/master
Author: Open Law Library
Author-email: info@openlawlib.org
Keywords: update updater secure authentication archival
Classifier: Development Status :: 2 - Pre-Alpha
Classifier: Intended Audience :: Developers
Classifier: Intended Audience :: Information Technology
Classifier: Topic :: Security
Classifier: Topic :: Software Development
Classifier: License :: OSI Approved :: GNU Affero General Public License v3 or later (AGPLv3+)
Classifier: Operating System :: OS Independent
Classifier: Programming Language :: Python :: 3
Classifier: Programming Language :: Python :: 3.8
Classifier: Programming Language :: Python :: 3.9
Classifier: Programming Language :: Python :: 3.10
Classifier: Programming Language :: Python :: 3.11
Classifier: Programming Language :: Python :: 3.12
Classifier: Programming Language :: Python :: Implementation :: CPython
License-File: LICENSE.md
Requires-Dist: cattrs>=23.1.2
Requires-Dist: click==8.*
Requires-Dist: colorama>=0.3.9
Requires-Dist: tuf==5.*
Requires-Dist: cryptography==43.0.*
Requires-Dist: securesystemslib==1.*
Requires-Dist: loguru==0.7.*
Requires-Dist: pygit2==1.9.*; python_version < "3.11"
Requires-Dist: pygit2==1.14.*; python_version >= "3.11"
Requires-Dist: pyOpenSSL==24.2.*
Requires-Dist: logdecorator==2.*
Requires-Dist: tomli==2.0.*
Provides-Extra: ci
Requires-Dist: bandit>=1.6.0; extra == "ci"
Requires-Dist: black==22.12.0; extra == "ci"
Requires-Dist: coverage==4.5.3; extra == "ci"
Requires-Dist: pre-commit>=1.18.3; extra == "ci"
Requires-Dist: pytest-cov==2.7.1; extra == "ci"
Requires-Dist: freezegun==0.3.15; extra == "ci"
Provides-Extra: test
Requires-Dist: pytest==8.*; extra == "test"
Requires-Dist: freezegun==0.3.15; extra == "test"
Requires-Dist: jsonschema==3.2.0; extra == "test"
Requires-Dist: jinja2==3.1.*; extra == "test"
Requires-Dist: pytest-mock==3.14.*; extra == "test"
Requires-Dist: pytest-benchmark==4.0.0; extra == "test"
Provides-Extra: dev
Requires-Dist: bandit>=1.6.0; extra == "dev"
Requires-Dist: black==22.12.0; extra == "dev"
Requires-Dist: pre-commit>=1.18.3; extra == "dev"
Provides-Extra: yubikey
Requires-Dist: yubikey-manager==5.8.*; extra == "yubikey"
Requires-Dist: pyscard==2.3.*; extra == "yubikey"
Provides-Extra: executable
Requires-Dist: lxml; extra == "executable"
Dynamic: author
Dynamic: author-email
Dynamic: classifier
Dynamic: description
Dynamic: description-content-type
Dynamic: home-page
Dynamic: keywords
Dynamic: license-file
Dynamic: provides-extra
Dynamic: requires-dist
Dynamic: summary
